{"assets":{"7D50DCF512C4D73F812622D1EC74D43E":{"type":"texture","index":82,"assetRequest":{"type":"slide","state":"object","slide":"FF44E24B-4C5E-4976-97EE-D14F368004F1"},"url":"assets/7D50DCF512C4D73F812622D1EC74D43E.svg","width":803,"height":4567},"999D1AE5944114C74E2AB63B4E8EE281":{"type":"texture","index":84,"assetRequest":{"type":"slide","state":"object","slide":"FF44E24B-4C5E-4976-97EE-D14F368004F1"},"url":"assets/999D1AE5944114C74E2AB63B4E8EE281.svg","width":250,"height":113},"FCE53940C0C3555566F19FEF0BB848A1":{"type":"texture","index":83,"assetRequest":{"type":"slide","state":"object","slide":"FF44E24B-4C5E-4976-97EE-D14F368004F1"},"url":"assets/FCE53940C0C3555566F19FEF0BB848A1.svg","width":260,"height":630},"498E23C82CA78A4BCD7BA88E5243B6FC":{"type":"texture","index":80,"assetRequest":{"type":"slide","state":"background","slide":"FF44E24B-4C5E-4976-97EE-D14F368004F1"},"url":"assets/498E23C82CA78A4BCD7BA88E5243B6FC.svg","width":1024,"height":768},"98B904E3103C9FADF2114C0AC0A731E4":{"type":"texture","index":88,"assetRequest":{"type":"slide","state":"object","slide":"FF44E24B-4C5E-4976-97EE-D14F368004F1"},"url":"assets/98B904E3103C9FADF2114C0AC0A731E4.svg","width":250,"height":126},"0C4FC08A4D7B7D9141DDC55C10A89D6D":{"type":"texture","index":85,"assetRequest":{"type":"slide","state":"object","slide":"FF44E24B-4C5E-4976-97EE-D14F368004F1"},"url":"assets/0C4FC08A4D7B7D9141DDC55C10A89D6D.svg","width":247,"height":109},"C10580EBB3A23C2FE6BD9903997612FF":{"type":"texture","index":89,"assetRequest":{"type":"slide","state":"object","slide":"FF44E24B-4C5E-4976-97EE-D14F368004F1"},"url":"assets/C10580EBB3A23C2FE6BD9903997612FF.svg","width":820,"height":126},"715C98E6A5D6F1362BEEBA74D1C39D4E":{"type":"texture","index":90,"assetRequest":{"type":"slide","state":"object","slide":"FF44E24B-4C5E-4976-97EE-D14F368004F1"},"url":"assets/715C98E6A5D6F1362BEEBA74D1C39D4E.svg","width":802,"height":74},"43C97FFBEA58A5B375EC8035CAD84961":{"type":"texture","index":92,"assetRequest":{"type":"slide","state":"object","slide":"FF44E24B-4C5E-4976-97EE-D14F368004F1"},"url":"assets/43C97FFBEA58A5B375EC8035CAD84961.svg","width":98,"height":38},"13909EA15F3D0356F5B38F505AA6C331":{"type":"texture","index":93,"assetRequest":{"type":"slide","state":"object","slide":"FF44E24B-4C5E-4976-97EE-D14F368004F1"},"url":"assets/13909EA15F3D0356F5B38F505AA6C331.svg","width":229,"height":85},"7827C96FF9C65AD2CFA3BE62C7DB7279":{"type":"texture","index":81,"assetRequest":{"type":"slide","state":"object","slide":"FF44E24B-4C5E-4976-97EE-D14F368004F1"},"url":"assets/7827C96FF9C65AD2CFA3BE62C7DB7279.svg","width":855,"height":102},"0FB63A3A657FBF105D42C27E1A52476A":{"type":"texture","index":91,"assetRequest":{"type":"slide","state":"object","slide":"FF44E24B-4C5E-4976-97EE-D14F368004F1"},"url":"assets/0FB63A3A657FBF105D42C27E1A52476A.svg","width":803,"height":42},"8B5FD83E7568DF35DE0A2052EA69B511":{"type":"texture","index":87,"assetRequest":{"type":"slide","state":"object","slide":"FF44E24B-4C5E-4976-97EE-D14F368004F1"},"url":"assets/8B5FD83E7568DF35DE0A2052EA69B511.svg","width":630,"height":149},"3348F4FAC70DB3704CD2F0BA33889034":{"type":"texture","index":86,"assetRequest":{"type":"slide","state":"object","slide":"FF44E24B-4C5E-4976-97EE-D14F368004F1"},"url":"assets/3348F4FAC70DB3704CD2F0BA33889034.svg","width":649,"height":143}},"events":[{"effects":[{"beginTime":0,"baseLayer":{"animations":[],"initialState":{"affineTransform":[1,0,0,1,0,0],"masksToBounds":true,"rotation":0,"scale":1,"position":{"pointX":512,"pointY":384},"width":1024,"sublayerTransform":[1,0,0,0,0,1,0,0,0,0,1,0,0,0,0,1],"contentsRect":{"y":0,"x":0,"width":1,"height":1},"opacity":1,"edgeAntialiasingMask":0,"height":768,"hidden":false,"anchorPoint":{"pointX":0.5,"pointY":0.5}},"objectID":"0","layers":[{"animations":[],"initialState":{"affineTransform":[1,0,0,1,0,0],"masksToBounds":false,"rotation":0,"scale":1,"position":{"pointX":512,"pointY":384},"width":1024,"sublayerTransform":[1,0,0,0,0,1,0,0,0,0,1,-0.0004922987690640373,0,0,0,1],"contentsRect":{"y":0,"x":0,"width":1,"height":1},"opacity":1,"edgeAntialiasingMask":15,"height":768,"hidden":false,"anchorPoint":{"pointX":0.5,"pointY":0.5}},"layers":[{"animations":[{"repeatCount":0,"animations":[{"from":{"scalar":0},"beginTime":0,"repeatCount":0,"fillMode":"both","property":"zPosition","duration":2,"timingFunction":"linear","to":{"scalar":0}}],"beginTime":0,"fillMode":"both","duration":2}],"initialState":{"affineTransform":[1,0,0,1,0,0],"masksToBounds":false,"rotation":0,"scale":1,"position":{"pointX":512,"pointY":384},"width":1024,"sublayerTransform":[1,0,0,0,0,1,0,0,0,0,1,0,0,0,0,1],"contentsRect":{"y":0,"x":0,"width":1,"height":1},"opacity":1,"edgeAntialiasingMask":15,"height":768,"hidden":false,"anchorPoint":{"pointX":0.5,"pointY":0.5}},"layers":[{"animations":[{"repeatCount":0,"animations":[{"from":{"texture":"498E23C82CA78A4BCD7BA88E5243B6FC"},"beginTime":0,"repeatCount":0,"fillMode":"both","property":"contents","duration":2,"timingFunction":"linear","to":{"texture":"498E23C82CA78A4BCD7BA88E5243B6FC"}}],"beginTime":0,"fillMode":"both","duration":2}],"layers":[],"initialState":{"affineTransform":[1,0,0,1,0,0],"masksToBounds":false,"rotation":0,"scale":1,"position":{"pointX":512,"pointY":384},"width":1024,"sublayerTransform":[1,0,0,0,0,1,0,0,0,0,1,0,0,0,0,1],"contentsRect":{"y":0,"x":0,"width":1,"height":1},"opacity":1,"edgeAntialiasingMask":0,"height":768,"hidden":false,"anchorPoint":{"pointX":0.5,"pointY":0.5}},"texture":"498E23C82CA78A4BCD7BA88E5243B6FC"}]}]},{"animations":[{"repeatCount":0,"animations":[{"from":{"scalar":0.001},"beginTime":0,"repeatCount":0,"fillMode":"both","property":"zPosition","duration":2,"timingFunction":"linear","to":{"scalar":0.001}}],"beginTime":0,"fillMode":"both","duration":2}],"initialState":{"affineTransform":[1,0,0,1,0,0],"masksToBounds":false,"rotation":0,"scale":1,"position":{"pointX":525.000036239624,"pointY":12},"width":851.9999504089355,"sublayerTransform":[1,0,0,0,0,1,0,0,0,0,1,0,0,0,0,1],"contentsRect":{"y":0,"x":0,"width":1,"height":1},"opacity":1,"edgeAntialiasingMask":15,"height":100,"hidden":false,"anchorPoint":{"pointX":0.5,"pointY":0.5}},"layers":[{"animations":[{"repeatCount":0,"animations":[{"from":{"texture":"7827C96FF9C65AD2CFA3BE62C7DB7279"},"beginTime":0,"repeatCount":0,"fillMode":"both","property":"contents","duration":2,"timingFunction":"linear","to":{"texture":"7827C96FF9C65AD2CFA3BE62C7DB7279"}}],"beginTime":0,"fillMode":"both","duration":2}],"layers":[],"initialState":{"affineTransform":[1,0,0,1,0,0],"masksToBounds":false,"rotation":0,"scale":1,"position":{"pointX":425.9999694824219,"pointY":50},"width":855,"sublayerTransform":[1,0,0,0,0,1,0,0,0,0,1,0,0,0,0,1],"contentsRect":{"y":0,"x":0,"width":1,"height":1},"opacity":1,"edgeAntialiasingMask":0,"height":102,"hidden":false,"anchorPoint":{"pointX":0.4994152403714364,"pointY":0.5}},"texture":"7827C96FF9C65AD2CFA3BE62C7DB7279"}]},{"animations":[{"repeatCount":0,"animations":[{"from":{"scalar":0.002},"beginTime":0,"repeatCount":0,"fillMode":"both","property":"zPosition","duration":2,"timingFunction":"linear","to":{"scalar":0.002}}],"beginTime":0,"fillMode":"both","duration":2}],"initialState":{"affineTransform":[1,0,0,1,0,0],"masksToBounds":false,"rotation":0,"scale":1,"position":{"pointX":513.2058181762695,"pointY":1184.20556640625},"width":800,"sublayerTransform":[1,0,0,0,0,1,0,0,0,0,1,0,0,0,0,1],"contentsRect":{"y":0,"x":0,"width":1,"height":1},"opacity":1,"edgeAntialiasingMask":15,"height":4563.7880859375,"hidden":false,"anchorPoint":{"pointX":0.5,"pointY":0.5}},"layers":[{"animations":[{"repeatCount":0,"animations":[{"from":{"texture":"7D50DCF512C4D73F812622D1EC74D43E"},"beginTime":0,"repeatCount":0,"fillMode":"both","property":"contents","duration":2,"timingFunction":"linear","to":{"texture":"7D50DCF512C4D73F812622D1EC74D43E"}},{"from":{"pointX":0,"pointY":0},"beginTime":0,"repeatCount":0,"fillMode":"both","property":"transform.translation","duration":2,"timingFunction":"linear","to":{"pointX":0,"pointY":-240}}],"beginTime":0,"fillMode":"both","duration":2}],"layers":[],"initialState":{"affineTransform":[1,0,0,1,0,0],"masksToBounds":false,"rotation":0,"scale":1,"position":{"pointX":400,"pointY":2281.89404296875},"width":803,"sublayerTransform":[1,0,0,0,0,1,0,0,0,0,1,0,0,0,0,1],"contentsRect":{"y":0,"x":0,"width":1,"height":1},"opacity":1,"edgeAntialiasingMask":0,"height":4567,"hidden":false,"anchorPoint":{"pointX":0.4996336465457902,"pointY":0.4999355301962448}},"texture":"7D50DCF512C4D73F812622D1EC74D43E"}]},{"animations":[{"repeatCount":0,"animations":[{"from":{"scalar":0.003},"beginTime":0,"repeatCount":0,"fillMode":"both","property":"zPosition","duration":2,"timingFunction":"linear","to":{"scalar":0.003}}],"beginTime":0,"fillMode":"both","duration":2}],"initialState":{"affineTransform":[1,0,0,1,0,0],"masksToBounds":false,"rotation":0,"scale":1,"position":{"pointX":295.7128925323486,"pointY":459.623188972473},"width":257.4257850646973,"sublayerTransform":[1,0,0,0,0,1,0,0,0,0,1,0,0,0,0,1],"contentsRect":{"y":0,"x":0,"width":1,"height":1},"opacity":1,"edgeAntialiasingMask":15,"height":626.8629550933838,"hidden":false,"anchorPoint":{"pointX":0.5,"pointY":0.5}},"layers":[{"animations":[{"repeatCount":0,"animations":[{"from":{"texture":"FCE53940C0C3555566F19FEF0BB848A1"},"beginTime":0,"repeatCount":0,"fillMode":"both","property":"contents","duration":2,"timingFunction":"linear","to":{"texture":"FCE53940C0C3555566F19FEF0BB848A1"}}],"beginTime":0,"fillMode":"both","duration":2}],"layers":[],"initialState":{"affineTransform":[1,0,0,1,0,0],"masksToBounds":false,"rotation":0,"scale":1,"position":{"pointX":128.712890625,"pointY":313.4314880371094},"width":260,"sublayerTransform":[1,0,0,0,0,1,0,0,0,0,1,0,0,0,0,1],"contentsRect":{"y":0,"x":0,"width":1,"height":1},"opacity":1,"edgeAntialiasingMask":0,"height":630,"hidden":false,"anchorPoint":{"pointX":0.4988957331730769,"pointY":0.49940190390935}},"texture":"FCE53940C0C3555566F19FEF0BB848A1"}]},{"animations":[{"repeatCount":0,"animations":[{"from":{"scalar":0.004},"beginTime":0,"repeatCount":0,"fillMode":"both","property":"zPosition","duration":2,"timingFunction":"linear","to":{"scalar":0.004}}],"beginTime":0,"fillMode":"both","duration":2}],"initialState":{"affineTransform":[1,0,0,1,0,0],"masksToBounds":false,"rotation":0,"scale":1,"position":{"pointX":310.06640625,"pointY":529.825855255127},"width":246.703125,"sublayerTransform":[1,0,0,0,0,1,0,0,0,0,1,0,0,0,0,1],"contentsRect":{"y":0,"x":0,"width":1,"height":1},"opacity":0,"edgeAntialiasingMask":15,"height":110.2454605102539,"hidden":false,"anchorPoint":{"pointX":0.5,"pointY":0.5}},"layers":[{"animations":[{"repeatCount":0,"animations":[{"from":{"scalar":false},"beginTime":1.9,"repeatCount":0,"fillMode":"forwards","property":"hidden","duration":0.1000000000000001,"to":{"scalar":false}}],"beginTime":0,"fillMode":"both","duration":2}],"layers":[],"initialState":{"affineTransform":[1,0,0,1,0,0],"masksToBounds":false,"rotation":0,"scale":1,"position":{"pointX":123.3515625,"pointY":55.12273025512695},"width":250,"sublayerTransform":[1,0,0,0,0,1,0,0,0,0,1,0,0,0,0,1],"contentsRect":{"y":0,"x":0,"width":1,"height":1},"opacity":1,"edgeAntialiasingMask":0,"height":113,"hidden":true,"anchorPoint":{"pointX":0.500265625,"pointY":0.5028836748241323}},"texture":"999D1AE5944114C74E2AB63B4E8EE281"}]},{"animations":[{"repeatCount":0,"animations":[{"from":{"scalar":0.005},"beginTime":0,"repeatCount":0,"fillMode":"both","property":"zPosition","duration":2,"timingFunction":"linear","to":{"scalar":0.006}}],"beginTime":0,"fillMode":"both","duration":2}],"initialState":{"affineTransform":[1,0,0,1,0,0],"masksToBounds":false,"rotation":0,"scale":1,"position":{"pointX":295.359375,"pointY":212.6406135559082},"width":244.71875,"sublayerTransform":[1,0,0,0,0,1,0,0,0,0,1,0,0,0,0,1],"contentsRect":{"y":0,"x":0,"width":1,"height":1},"opacity":1,"edgeAntialiasingMask":15,"height":105.90625,"hidden":false,"anchorPoint":{"pointX":0.5,"pointY":0.5}},"layers":[{"animations":[{"repeatCount":0,"animations":[{"from":{"texture":"0C4FC08A4D7B7D9141DDC55C10A89D6D"},"beginTime":0,"repeatCount":0,"fillMode":"both","property":"contents","duration":2,"timingFunction":"linear","to":{"texture":"0C4FC08A4D7B7D9141DDC55C10A89D6D"}},{"from":{"pointX":0,"pointY":0},"beginTime":0,"repeatCount":0,"fillMode":"both","property":"transform.translation","duration":2,"timingFunction":"linear","to":{"pointX":0,"pointY":-120}}],"beginTime":0,"fillMode":"both","duration":2}],"layers":[],"initialState":{"affineTransform":[1,0,0,1,0,0],"masksToBounds":false,"rotation":0,"scale":1,"position":{"pointX":122.3515629768372,"pointY":52.95116901397705},"width":247,"sublayerTransform":[1,0,0,0,0,1,0,0,0,0,1,0,0,0,0,1],"contentsRect":{"y":0,"x":0,"width":1,"height":1},"opacity":1,"edgeAntialiasingMask":0,"height":109,"hidden":false,"anchorPoint":{"pointX":0.4993990403920533,"pointY":0.5012720877971124}},"texture":"0C4FC08A4D7B7D9141DDC55C10A89D6D"}]},{"animations":[{"repeatCount":0,"animations":[{"from":{"scalar":0.006},"beginTime":0,"repeatCount":0,"fillMode":"both","property":"zPosition","duration":2,"timingFunction":"linear","to":{"scalar":0.007}}],"beginTime":0,"fillMode":"both","duration":2}],"initialState":{"affineTransform":[1,0,0,1,0,0],"masksToBounds":false,"rotation":0,"scale":1,"position":{"pointX":488.7109375,"pointY":95.79092884063721},"width":646.484375,"sublayerTransform":[1,0,0,0,0,1,0,0,0,0,1,0,0,0,0,1],"contentsRect":{"y":0,"x":0,"width":1,"height":1},"opacity":1,"edgeAntialiasingMask":15,"height":140.0000095367432,"hidden":false,"anchorPoint":{"pointX":0.5,"pointY":0.5}},"layers":[{"animations":[{"repeatCount":0,"animations":[{"from":{"texture":"3348F4FAC70DB3704CD2F0BA33889034"},"beginTime":0,"repeatCount":0,"fillMode":"both","property":"contents","duration":2,"timingFunction":"linear","to":{"texture":"3348F4FAC70DB3704CD2F0BA33889034"}}],"beginTime":0,"fillMode":"both","duration":2}],"layers":[],"initialState":{"affineTransform":[1,0,0,1,0,0],"masksToBounds":false,"rotation":0,"scale":1,"position":{"pointX":323.2421875,"pointY":70.00000762939453},"width":649,"sublayerTransform":[1,0,0,0,0,1,0,0,0,0,1,0,0,0,0,1],"contentsRect":{"y":0,"x":0,"width":1,"height":1},"opacity":1,"edgeAntialiasingMask":0,"height":143,"hidden":false,"anchorPoint":{"pointX":0.5003250192604006,"pointY":0.5020344874241969}},"texture":"3348F4FAC70DB3704CD2F0BA33889034"}]},{"animations":[{"repeatCount":0,"animations":[{"from":{"scalar":0.007},"beginTime":0,"repeatCount":0,"fillMode":"both","property":"zPosition","duration":2,"timingFunction":"linear","to":{"scalar":0.008}}],"beginTime":0,"fillMode":"both","duration":2}],"initialState":{"affineTransform":[1,0,0,1,0,0],"masksToBounds":false,"rotation":0,"scale":1,"position":{"pointX":500.5586090087891,"pointY":27.47647166252136},"width":627.0390510559082,"sublayerTransform":[1,0,0,0,0,1,0,0,0,0,1,0,0,0,0,1],"contentsRect":{"y":0,"x":0,"width":1,"height":1},"opacity":1,"edgeAntialiasingMask":15,"height":145.3710913658142,"hidden":false,"anchorPoint":{"pointX":0.5,"pointY":0.5}},"layers":[{"animations":[{"repeatCount":0,"animations":[{"from":{"texture":"8B5FD83E7568DF35DE0A2052EA69B511"},"beginTime":0,"repeatCount":0,"fillMode":"both","property":"contents","duration":2,"timingFunction":"linear","to":{"texture":"8B5FD83E7568DF35DE0A2052EA69B511"}}],"beginTime":0,"fillMode":"both","duration":2}],"layers":[],"initialState":{"affineTransform":[1,0,0,1,0,0],"masksToBounds":false,"rotation":0,"scale":1,"position":{"pointX":313.5195255279541,"pointY":72.6855456829071},"width":630,"sublayerTransform":[1,0,0,0,0,1,0,0,0,0,1,0,0,0,0,1],"contentsRect":{"y":0,"x":0,"width":1,"height":1},"opacity":1,"edgeAntialiasingMask":0,"height":149,"hidden":false,"anchorPoint":{"pointX":0.4992993793790302,"pointY":0.4998420916947742}},"texture":"8B5FD83E7568DF35DE0A2052EA69B511"}]},{"animations":[{"repeatCount":0,"animations":[{"from":{"scalar":0.008},"beginTime":0,"repeatCount":0,"fillMode":"both","property":"zPosition","duration":2,"timingFunction":"linear","to":{"scalar":0.009000000000000001}}],"beginTime":0,"fillMode":"both","duration":2}],"initialState":{"affineTransform":[1,0,0,1,0,0],"masksToBounds":false,"rotation":0,"scale":1,"position":{"pointX":310.06640625,"pointY":105.7431030273438},"width":246.703125,"sublayerTransform":[1,0,0,0,0,1,0,0,0,0,1,0,0,0,0,1],"contentsRect":{"y":0,"x":0,"width":1,"height":1},"opacity":1,"edgeAntialiasingMask":15,"height":123.3515625,"hidden":false,"anchorPoint":{"pointX":0.5,"pointY":0.5}},"layers":[{"animations":[{"repeatCount":0,"animations":[{"from":{"texture":"98B904E3103C9FADF2114C0AC0A731E4"},"beginTime":0,"repeatCount":0,"fillMode":"both","property":"contents","duration":2,"timingFunction":"linear","to":{"texture":"98B904E3103C9FADF2114C0AC0A731E4"}}],"beginTime":0,"fillMode":"both","duration":2}],"layers":[],"initialState":{"affineTransform":[1,0,0,1,0,0],"masksToBounds":false,"rotation":0,"scale":1,"position":{"pointX":123.3515625,"pointY":61.67578125},"width":250,"sublayerTransform":[1,0,0,0,0,1,0,0,0,0,1,0,0,0,0,1],"contentsRect":{"y":0,"x":0,"width":1,"height":1},"opacity":1,"edgeAntialiasingMask":0,"height":126,"hidden":false,"anchorPoint":{"pointX":0.500265625,"pointY":0.4979611351376488}},"texture":"98B904E3103C9FADF2114C0AC0A731E4"}]},{"animations":[{"repeatCount":0,"animations":[{"from":{"scalar":0.009000000000000001},"beginTime":0,"repeatCount":0,"fillMode":"both","property":"zPosition","duration":2,"timingFunction":"linear","to":{"scalar":0.01}}],"beginTime":0,"fillMode":"both","duration":2}],"initialState":{"affineTransform":[1,0,0,1,0,0],"masksToBounds":false,"rotation":0,"scale":1,"position":{"pointX":517.8496208190918,"pointY":57.13250708580017},"width":817.6992416381836,"sublayerTransform":[1,0,0,0,0,1,0,0,0,0,1,0,0,0,0,1],"contentsRect":{"y":0,"x":0,"width":1,"height":1},"opacity":1,"edgeAntialiasingMask":15,"height":123.3515620231628,"hidden":false,"anchorPoint":{"pointX":0.5,"pointY":0.5}},"layers":[{"animations":[{"repeatCount":0,"animations":[{"from":{"texture":"C10580EBB3A23C2FE6BD9903997612FF"},"beginTime":0,"repeatCount":0,"fillMode":"both","property":"contents","duration":2,"timingFunction":"linear","to":{"texture":"C10580EBB3A23C2FE6BD9903997612FF"}}],"beginTime":0,"fillMode":"both","duration":2}],"layers":[],"initialState":{"affineTransform":[1,0,0,1,0,0],"masksToBounds":false,"rotation":0,"scale":1,"position":{"pointX":408.849609375,"pointY":61.67578125},"width":820,"sublayerTransform":[1,0,0,0,0,1,0,0,0,0,1,0,0,0,0,1],"contentsRect":{"y":0,"x":0,"width":1,"height":1},"opacity":1,"edgeAntialiasingMask":0,"height":126,"hidden":false,"anchorPoint":{"pointX":0.4998165967987805,"pointY":0.5010516454303076}},"texture":"C10580EBB3A23C2FE6BD9903997612FF"}]},{"animations":[{"repeatCount":0,"animations":[{"from":{"scalar":0.01},"beginTime":0,"repeatCount":0,"fillMode":"both","property":"zPosition","duration":2,"timingFunction":"linear","to":{"scalar":0.011}}],"beginTime":0,"fillMode":"both","duration":2}],"initialState":{"affineTransform":[1,0,0,1,0,0],"masksToBounds":false,"rotation":0,"scale":1,"position":{"pointX":512,"pointY":95.31640625},"width":800,"sublayerTransform":[1,0,0,0,0,1,0,0,0,0,1,0,0,0,0,1],"contentsRect":{"y":0,"x":0,"width":1,"height":1},"opacity":1,"edgeAntialiasingMask":15,"height":71,"hidden":false,"anchorPoint":{"pointX":0.5,"pointY":0.5}},"layers":[{"animations":[{"repeatCount":0,"animations":[{"from":{"texture":"715C98E6A5D6F1362BEEBA74D1C39D4E"},"beginTime":0,"repeatCount":0,"fillMode":"both","property":"contents","duration":2,"timingFunction":"linear","to":{"texture":"715C98E6A5D6F1362BEEBA74D1C39D4E"}}],"beginTime":0,"fillMode":"both","duration":2}],"layers":[],"initialState":{"affineTransform":[1,0,0,1,0,0],"masksToBounds":false,"rotation":0,"scale":1,"position":{"pointX":400,"pointY":35.5},"width":802,"sublayerTransform":[1,0,0,0,0,1,0,0,0,0,1,0,0,0,0,1],"contentsRect":{"y":0,"x":0,"width":1,"height":1},"opacity":1,"edgeAntialiasingMask":0,"height":74,"hidden":false,"anchorPoint":{"pointX":0.5,"pointY":0.5042757601351351}},"texture":"715C98E6A5D6F1362BEEBA74D1C39D4E"}]},{"animations":[{"repeatCount":0,"animations":[{"from":{"scalar":0.011},"beginTime":0,"repeatCount":0,"fillMode":"both","property":"zPosition","duration":2,"timingFunction":"linear","to":{"scalar":0.012}}],"beginTime":0,"fillMode":"both","duration":2}],"initialState":{"affineTransform":[1,0,0,1,0,0],"masksToBounds":false,"rotation":0,"scale":1,"position":{"pointX":513.205810546875,"pointY":149.8984317779541},"width":799.9999389648438,"sublayerTransform":[1,0,0,0,0,1,0,0,0,0,1,0,0,0,0,1],"contentsRect":{"y":0,"x":0,"width":1,"height":1},"opacity":1,"edgeAntialiasingMask":15,"height":38.80208206176758,"hidden":false,"anchorPoint":{"pointX":0.5,"pointY":0.5}},"layers":[{"animations":[{"repeatCount":0,"animations":[{"from":{"texture":"0FB63A3A657FBF105D42C27E1A52476A"},"beginTime":0,"repeatCount":0,"fillMode":"both","property":"contents","duration":2,"timingFunction":"linear","to":{"texture":"0FB63A3A657FBF105D42C27E1A52476A"}}],"beginTime":0,"fillMode":"both","duration":2}],"layers":[],"initialState":{"affineTransform":[1,0,0,1,0,0],"masksToBounds":false,"rotation":0,"scale":1,"position":{"pointX":399.9999694824219,"pointY":19.40104103088379},"width":803,"sublayerTransform":[1,0,0,0,0,1,0,0,0,0,1,0,0,0,0,1],"contentsRect":{"y":0,"x":0,"width":1,"height":1},"opacity":1,"edgeAntialiasingMask":0,"height":42,"hidden":false,"anchorPoint":{"pointX":0.4996336370446762,"pointY":0.4975817089989072}},"texture":"0FB63A3A657FBF105D42C27E1A52476A"}]},{"animations":[{"repeatCount":0,"animations":[{"from":{"scalar":0.012},"beginTime":0,"repeatCount":0,"fillMode":"both","property":"zPosition","duration":2,"timingFunction":"linear","to":{"scalar":0.013}}],"beginTime":0,"fillMode":"both","duration":2}],"initialState":{"affineTransform":[1,0,0,1,0,0],"masksToBounds":false,"rotation":0,"scale":1,"position":{"pointX":338.5703134536743,"pointY":149.8984318375587},"width":94.87500190734863,"sublayerTransform":[1,0,0,0,0,1,0,0,0,0,1,0,0,0,0,1],"contentsRect":{"y":0,"x":0,"width":1,"height":1},"opacity":0.6047312021255493,"edgeAntialiasingMask":15,"height":35.27281582355499,"hidden":false,"anchorPoint":{"pointX":0.5,"pointY":0.5}},"layers":[{"animations":[{"repeatCount":0,"animations":[{"from":{"texture":"43C97FFBEA58A5B375EC8035CAD84961"},"beginTime":0,"repeatCount":0,"fillMode":"both","property":"contents","duration":2,"timingFunction":"linear","to":{"texture":"43C97FFBEA58A5B375EC8035CAD84961"}}],"beginTime":0,"fillMode":"both","duration":2}],"layers":[],"initialState":{"affineTransform":[1,0,0,1,0,0],"masksToBounds":false,"rotation":0,"scale":1,"position":{"pointX":47.4375,"pointY":17.63640785217285},"width":98,"sublayerTransform":[1,0,0,0,0,1,0,0,0,0,1,0,0,0,0,1],"contentsRect":{"y":0,"x":0,"width":1,"height":1},"opacity":1,"edgeAntialiasingMask":0,"height":38,"hidden":false,"anchorPoint":{"pointX":0.4956154336734694,"pointY":0.4973271520514237}},"texture":"43C97FFBEA58A5B375EC8035CAD84961"}]},{"animations":[{"repeatCount":0,"animations":[{"from":{"scalar":1},"beginTime":0,"repeatCount":0,"fillMode":"both","property":"opacity","duration":2,"timingFunction":"linear","to":{"scalar":1}},{"from":{"scalar":0.013},"beginTime":0,"repeatCount":0,"fillMode":"both","property":"zPosition","duration":2,"timingFunction":"linear","to":{"scalar":0.005}}],"beginTime":0,"fillMode":"both","duration":2}],"initialState":{"affineTransform":[1,0,0,1,0,0],"masksToBounds":false,"rotation":0,"scale":1,"position":{"pointX":310.0664062500001,"pointY":463.4370002746581},"width":225.9102630615235,"sublayerTransform":[1,0,0,0,0,1,0,0,0,0,1,0,0,0,0,1],"contentsRect":{"y":0,"x":0,"width":1,"height":1},"opacity":0,"edgeAntialiasingMask":15,"height":81.18650054931641,"hidden":false,"anchorPoint":{"pointX":0.5,"pointY":0.5}},"layers":[{"animations":[{"repeatCount":0,"animations":[{"from":{"texture":"13909EA15F3D0356F5B38F505AA6C331"},"beginTime":0,"repeatCount":0,"fillMode":"both","property":"contents","duration":2,"timingFunction":"linear","to":{"texture":"13909EA15F3D0356F5B38F505AA6C331"}},{"from":{"pointX":0,"pointY":0},"beginTime":0,"repeatCount":0,"fillMode":"both","property":"transform.translation","duration":2,"timingFunction":"linear","to":{"pointX":0,"pointY":-250}},{"from":{"scalar":0},"beginTime":0,"repeatCount":0,"fillMode":"both","property":"opacity","duration":2,"timingFunction":"linear","to":{"scalar":1}}],"beginTime":0,"fillMode":"both","duration":2}],"layers":[],"initialState":{"affineTransform":[1,0,0,1,0,0],"masksToBounds":false,"rotation":0,"scale":1,"position":{"pointX":112.9551315307617,"pointY":40.5932502746582},"width":229,"sublayerTransform":[1,0,0,0,0,1,0,0,0,0,1,0,0,0,0,1],"contentsRect":{"y":0,"x":0,"width":1,"height":1},"opacity":1,"edgeAntialiasingMask":0,"height":85,"hidden":false,"anchorPoint":{"pointX":0.4981065775109173,"pointY":0.4992588267606834}},"texture":"13909EA15F3D0356F5B38F505AA6C331"}]}]},"effects":[],"duration":2,"type":"transition","name":"apple:magic-move-implied-motion-path","objectID":"0"}],"automaticPlay":true,"hyperlinks":[],"accessibility":[{"text":"d-jdb-small.png","targetRectangle":{"y":-1097.6884765625,"x":113.2058181762695,"width":800,"height":4563.7880859375}},{"text":"narr-3.png","targetRectangle":{"y":422.8437499999999,"x":197.1112747192383,"width":225.9102630615235,"height":81.18650054931641}},{"text":"narr-2.png","targetRectangle":{"y":159.6874885559082,"x":173,"width":244.71875,"height":105.90625}},{"text":"narr-1.png","targetRectangle":{"y":44.06732177734375,"x":186.71484375,"width":246.703125,"height":123.3515625}},{"text":"Google-Chrome-Flat-Browser.png","targetRectangle":{"y":59.81640625,"x":112,"width":800,"height":71}},{"text":"d-jdb-local-nav.png","targetRectangle":{"y":130.4973907470703,"x":113.2058410644531,"width":799.9999389648438,"height":38.80208206176758}},{"text":"intro.jpg","targetRectangle":{"y":-45.20907402038574,"x":187.039083480835,"width":627.0390510559082,"height":145.3710913658142}}],"baseLayer":{"animations":[],"initialState":{"affineTransform":[1,0,0,1,0,0],"masksToBounds":true,"rotation":0,"scale":1,"position":{"pointX":512,"pointY":384},"width":1024,"sublayerTransform":[1,0,0,0,0,1,0,0,0,0,1,0,0,0,0,1],"contentsRect":{"y":0,"x":0,"width":1,"height":1},"opacity":1,"edgeAntialiasingMask":0,"height":768,"hidden":false,"anchorPoint":{"pointX":0.5,"pointY":0.5}},"objectID":"0","layers":[{"animations":[],"initialState":{"affineTransform":[1,0,0,1,0,0],"masksToBounds":false,"rotation":0,"scale":1,"position":{"pointX":512,"pointY":384},"width":1024,"sublayerTransform":[1,0,0,0,0,1,0,0,0,0,1,-0.0004922987690640373,0,0,0,1],"contentsRect":{"y":0,"x":0,"width":1,"height":1},"opacity":1,"edgeAntialiasingMask":15,"height":768,"hidden":false,"anchorPoint":{"pointX":0.5,"pointY":0.5}},"layers":[{"animations":[],"initialState":{"affineTransform":[1,0,0,1,0,0],"masksToBounds":false,"rotation":0,"scale":1,"position":{"pointX":512,"pointY":384},"width":1024,"sublayerTransform":[1,0,0,0,0,1,0,0,0,0,1,0,0,0,0,1],"contentsRect":{"y":0,"x":0,"width":1,"height":1},"opacity":1,"edgeAntialiasingMask":15,"height":768,"hidden":false,"anchorPoint":{"pointX":0.5,"pointY":0.5}},"layers":[{"animations":[],"layers":[],"initialState":{"affineTransform":[1,0,0,1,0,0],"masksToBounds":false,"rotation":0,"scale":1,"position":{"pointX":512,"pointY":384},"width":1024,"sublayerTransform":[1,0,0,0,0,1,0,0,0,0,1,0,0,0,0,1],"contentsRect":{"y":0,"x":0,"width":1,"height":1},"opacity":1,"edgeAntialiasingMask":0,"height":768,"hidden":false,"anchorPoint":{"pointX":0.5,"pointY":0.5}},"texture":"498E23C82CA78A4BCD7BA88E5243B6FC"}]}]},{"animations":[],"initialState":{"affineTransform":[1,0,0,1,0,0],"masksToBounds":false,"rotation":0,"scale":1,"position":{"pointX":525.000036239624,"pointY":12},"width":851.9999504089355,"sublayerTransform":[1,0,0,0,0,1,0,0,0,0,1,0,0,0,0,1],"contentsRect":{"y":0,"x":0,"width":1,"height":1},"opacity":1,"edgeAntialiasingMask":15,"height":100,"hidden":false,"anchorPoint":{"pointX":0.5,"pointY":0.5}},"layers":[{"animations":[],"layers":[],"initialState":{"affineTransform":[1,0,0,1,0,0],"masksToBounds":false,"rotation":0,"scale":1,"position":{"pointX":425.9999694824219,"pointY":50},"width":855,"sublayerTransform":[1,0,0,0,0,1,0,0,0,0,1,0,0,0,0,1],"contentsRect":{"y":0,"x":0,"width":1,"height":1},"opacity":1,"edgeAntialiasingMask":0,"height":102,"hidden":false,"anchorPoint":{"pointX":0.4994152403714364,"pointY":0.5}},"texture":"7827C96FF9C65AD2CFA3BE62C7DB7279"}]},{"animations":[],"initialState":{"affineTransform":[1,0,0,1,0,0],"masksToBounds":false,"rotation":0,"scale":1,"position":{"pointX":513.2058181762695,"pointY":1184.20556640625},"width":800,"sublayerTransform":[1,0,0,0,0,1,0,0,0,0,1,0,0,0,0,1],"contentsRect":{"y":0,"x":0,"width":1,"height":1},"opacity":1,"edgeAntialiasingMask":15,"height":4563.7880859375,"hidden":false,"anchorPoint":{"pointX":0.5,"pointY":0.5}},"layers":[{"animations":[],"layers":[],"initialState":{"affineTransform":[1,0,0,1,0,0],"masksToBounds":false,"rotation":0,"scale":1,"position":{"pointX":400,"pointY":2281.89404296875},"width":803,"sublayerTransform":[1,0,0,0,0,1,0,0,0,0,1,0,0,0,0,1],"contentsRect":{"y":0,"x":0,"width":1,"height":1},"opacity":1,"edgeAntialiasingMask":0,"height":4567,"hidden":false,"anchorPoint":{"pointX":0.4996336465457902,"pointY":0.4999355301962448}},"texture":"7D50DCF512C4D73F812622D1EC74D43E"}]},{"animations":[],"initialState":{"affineTransform":[1,0,0,1,0,0],"masksToBounds":false,"rotation":0,"scale":1,"position":{"pointX":295.7128925323486,"pointY":459.623188972473},"width":257.4257850646973,"sublayerTransform":[1,0,0,0,0,1,0,0,0,0,1,0,0,0,0,1],"contentsRect":{"y":0,"x":0,"width":1,"height":1},"opacity":1,"edgeAntialiasingMask":15,"height":626.8629550933838,"hidden":false,"anchorPoint":{"pointX":0.5,"pointY":0.5}},"layers":[{"animations":[],"layers":[],"initialState":{"affineTransform":[1,0,0,1,0,0],"masksToBounds":false,"rotation":0,"scale":1,"position":{"pointX":128.712890625,"pointY":313.4314880371094},"width":260,"sublayerTransform":[1,0,0,0,0,1,0,0,0,0,1,0,0,0,0,1],"contentsRect":{"y":0,"x":0,"width":1,"height":1},"opacity":1,"edgeAntialiasingMask":0,"height":630,"hidden":false,"anchorPoint":{"pointX":0.4988957331730769,"pointY":0.49940190390935}},"texture":"FCE53940C0C3555566F19FEF0BB848A1"}]},{"animations":[],"initialState":{"affineTransform":[1,0,0,1,0,0],"masksToBounds":false,"rotation":0,"scale":1,"position":{"pointX":310.06640625,"pointY":529.825855255127},"width":246.703125,"sublayerTransform":[1,0,0,0,0,1,0,0,0,0,1,0,0,0,0,1],"contentsRect":{"y":0,"x":0,"width":1,"height":1},"opacity":0,"edgeAntialiasingMask":15,"height":110.2454605102539,"hidden":false,"anchorPoint":{"pointX":0.5,"pointY":0.5}},"layers":[{"animations":[],"layers":[],"initialState":{"affineTransform":[1,0,0,1,0,0],"masksToBounds":false,"rotation":0,"scale":1,"position":{"pointX":123.3515625,"pointY":55.12273025512695},"width":250,"sublayerTransform":[1,0,0,0,0,1,0,0,0,0,1,0,0,0,0,1],"contentsRect":{"y":0,"x":0,"width":1,"height":1},"opacity":1,"edgeAntialiasingMask":0,"height":113,"hidden":true,"anchorPoint":{"pointX":0.500265625,"pointY":0.5028836748241323}},"texture":"999D1AE5944114C74E2AB63B4E8EE281"}]},{"animations":[],"initialState":{"affineTransform":[1,0,0,1,0,0],"masksToBounds":false,"rotation":0,"scale":1,"position":{"pointX":295.359375,"pointY":212.6406135559082},"width":244.71875,"sublayerTransform":[1,0,0,0,0,1,0,0,0,0,1,0,0,0,0,1],"contentsRect":{"y":0,"x":0,"width":1,"height":1},"opacity":1,"edgeAntialiasingMask":15,"height":105.90625,"hidden":false,"anchorPoint":{"pointX":0.5,"pointY":0.5}},"layers":[{"animations":[],"layers":[],"initialState":{"affineTransform":[1,0,0,1,0,0],"masksToBounds":false,"rotation":0,"scale":1,"position":{"pointX":122.3515629768372,"pointY":52.95116901397705},"width":247,"sublayerTransform":[1,0,0,0,0,1,0,0,0,0,1,0,0,0,0,1],"contentsRect":{"y":0,"x":0,"width":1,"height":1},"opacity":1,"edgeAntialiasingMask":0,"height":109,"hidden":false,"anchorPoint":{"pointX":0.4993990403920533,"pointY":0.5012720877971124}},"texture":"0C4FC08A4D7B7D9141DDC55C10A89D6D"}]},{"animations":[],"initialState":{"affineTransform":[1,0,0,1,0,0],"masksToBounds":false,"rotation":0,"scale":1,"position":{"pointX":488.7109375,"pointY":95.79092884063721},"width":646.484375,"sublayerTransform":[1,0,0,0,0,1,0,0,0,0,1,0,0,0,0,1],"contentsRect":{"y":0,"x":0,"width":1,"height":1},"opacity":1,"edgeAntialiasingMask":15,"height":140.0000095367432,"hidden":false,"anchorPoint":{"pointX":0.5,"pointY":0.5}},"layers":[{"animations":[],"layers":[],"initialState":{"affineTransform":[1,0,0,1,0,0],"masksToBounds":false,"rotation":0,"scale":1,"position":{"pointX":323.2421875,"pointY":70.00000762939453},"width":649,"sublayerTransform":[1,0,0,0,0,1,0,0,0,0,1,0,0,0,0,1],"contentsRect":{"y":0,"x":0,"width":1,"height":1},"opacity":1,"edgeAntialiasingMask":0,"height":143,"hidden":false,"anchorPoint":{"pointX":0.5003250192604006,"pointY":0.5020344874241969}},"texture":"3348F4FAC70DB3704CD2F0BA33889034"}]},{"animations":[],"initialState":{"affineTransform":[1,0,0,1,0,0],"masksToBounds":false,"rotation":0,"scale":1,"position":{"pointX":500.5586090087891,"pointY":27.47647166252136},"width":627.0390510559082,"sublayerTransform":[1,0,0,0,0,1,0,0,0,0,1,0,0,0,0,1],"contentsRect":{"y":0,"x":0,"width":1,"height":1},"opacity":1,"edgeAntialiasingMask":15,"height":145.3710913658142,"hidden":false,"anchorPoint":{"pointX":0.5,"pointY":0.5}},"layers":[{"animations":[],"layers":[],"initialState":{"affineTransform":[1,0,0,1,0,0],"masksToBounds":false,"rotation":0,"scale":1,"position":{"pointX":313.5195255279541,"pointY":72.6855456829071},"width":630,"sublayerTransform":[1,0,0,0,0,1,0,0,0,0,1,0,0,0,0,1],"contentsRect":{"y":0,"x":0,"width":1,"height":1},"opacity":1,"edgeAntialiasingMask":0,"height":149,"hidden":false,"anchorPoint":{"pointX":0.4992993793790302,"pointY":0.4998420916947742}},"texture":"8B5FD83E7568DF35DE0A2052EA69B511"}]},{"animations":[],"initialState":{"affineTransform":[1,0,0,1,0,0],"masksToBounds":false,"rotation":0,"scale":1,"position":{"pointX":310.06640625,"pointY":105.7431030273438},"width":246.703125,"sublayerTransform":[1,0,0,0,0,1,0,0,0,0,1,0,0,0,0,1],"contentsRect":{"y":0,"x":0,"width":1,"height":1},"opacity":1,"edgeAntialiasingMask":15,"height":123.3515625,"hidden":false,"anchorPoint":{"pointX":0.5,"pointY":0.5}},"layers":[{"animations":[],"layers":[],"initialState":{"affineTransform":[1,0,0,1,0,0],"masksToBounds":false,"rotation":0,"scale":1,"position":{"pointX":123.3515625,"pointY":61.67578125},"width":250,"sublayerTransform":[1,0,0,0,0,1,0,0,0,0,1,0,0,0,0,1],"contentsRect":{"y":0,"x":0,"width":1,"height":1},"opacity":1,"edgeAntialiasingMask":0,"height":126,"hidden":false,"anchorPoint":{"pointX":0.500265625,"pointY":0.4979611351376488}},"texture":"98B904E3103C9FADF2114C0AC0A731E4"}]},{"animations":[],"initialState":{"affineTransform":[1,0,0,1,0,0],"masksToBounds":false,"rotation":0,"scale":1,"position":{"pointX":517.8496208190918,"pointY":57.13250708580017},"width":817.6992416381836,"sublayerTransform":[1,0,0,0,0,1,0,0,0,0,1,0,0,0,0,1],"contentsRect":{"y":0,"x":0,"width":1,"height":1},"opacity":1,"edgeAntialiasingMask":15,"height":123.3515620231628,"hidden":false,"anchorPoint":{"pointX":0.5,"pointY":0.5}},"layers":[{"animations":[],"layers":[],"initialState":{"affineTransform":[1,0,0,1,0,0],"masksToBounds":false,"rotation":0,"scale":1,"position":{"pointX":408.849609375,"pointY":61.67578125},"width":820,"sublayerTransform":[1,0,0,0,0,1,0,0,0,0,1,0,0,0,0,1],"contentsRect":{"y":0,"x":0,"width":1,"height":1},"opacity":1,"edgeAntialiasingMask":0,"height":126,"hidden":false,"anchorPoint":{"pointX":0.4998165967987805,"pointY":0.5010516454303076}},"texture":"C10580EBB3A23C2FE6BD9903997612FF"}]},{"animations":[],"initialState":{"affineTransform":[1,0,0,1,0,0],"masksToBounds":false,"rotation":0,"scale":1,"position":{"pointX":512,"pointY":95.31640625},"width":800,"sublayerTransform":[1,0,0,0,0,1,0,0,0,0,1,0,0,0,0,1],"contentsRect":{"y":0,"x":0,"width":1,"height":1},"opacity":1,"edgeAntialiasingMask":15,"height":71,"hidden":false,"anchorPoint":{"pointX":0.5,"pointY":0.5}},"layers":[{"animations":[],"layers":[],"initialState":{"affineTransform":[1,0,0,1,0,0],"masksToBounds":false,"rotation":0,"scale":1,"position":{"pointX":400,"pointY":35.5},"width":802,"sublayerTransform":[1,0,0,0,0,1,0,0,0,0,1,0,0,0,0,1],"contentsRect":{"y":0,"x":0,"width":1,"height":1},"opacity":1,"edgeAntialiasingMask":0,"height":74,"hidden":false,"anchorPoint":{"pointX":0.5,"pointY":0.5042757601351351}},"texture":"715C98E6A5D6F1362BEEBA74D1C39D4E"}]},{"animations":[],"initialState":{"affineTransform":[1,0,0,1,0,0],"masksToBounds":false,"rotation":0,"scale":1,"position":{"pointX":513.205810546875,"pointY":149.8984317779541},"width":799.9999389648438,"sublayerTransform":[1,0,0,0,0,1,0,0,0,0,1,0,0,0,0,1],"contentsRect":{"y":0,"x":0,"width":1,"height":1},"opacity":1,"edgeAntialiasingMask":15,"height":38.80208206176758,"hidden":false,"anchorPoint":{"pointX":0.5,"pointY":0.5}},"layers":[{"animations":[],"layers":[],"initialState":{"affineTransform":[1,0,0,1,0,0],"masksToBounds":false,"rotation":0,"scale":1,"position":{"pointX":399.9999694824219,"pointY":19.40104103088379},"width":803,"sublayerTransform":[1,0,0,0,0,1,0,0,0,0,1,0,0,0,0,1],"contentsRect":{"y":0,"x":0,"width":1,"height":1},"opacity":1,"edgeAntialiasingMask":0,"height":42,"hidden":false,"anchorPoint":{"pointX":0.4996336370446762,"pointY":0.4975817089989072}},"texture":"0FB63A3A657FBF105D42C27E1A52476A"}]},{"animations":[],"initialState":{"affineTransform":[1,0,0,1,0,0],"masksToBounds":false,"rotation":0,"scale":1,"position":{"pointX":338.5703134536743,"pointY":149.8984318375587},"width":94.87500190734863,"sublayerTransform":[1,0,0,0,0,1,0,0,0,0,1,0,0,0,0,1],"contentsRect":{"y":0,"x":0,"width":1,"height":1},"opacity":0.6047312021255493,"edgeAntialiasingMask":15,"height":35.27281582355499,"hidden":false,"anchorPoint":{"pointX":0.5,"pointY":0.5}},"layers":[{"animations":[],"layers":[],"initialState":{"affineTransform":[1,0,0,1,0,0],"masksToBounds":false,"rotation":0,"scale":1,"position":{"pointX":47.4375,"pointY":17.63640785217285},"width":98,"sublayerTransform":[1,0,0,0,0,1,0,0,0,0,1,0,0,0,0,1],"contentsRect":{"y":0,"x":0,"width":1,"height":1},"opacity":1,"edgeAntialiasingMask":0,"height":38,"hidden":false,"anchorPoint":{"pointX":0.4956154336734694,"pointY":0.4973271520514237}},"texture":"43C97FFBEA58A5B375EC8035CAD84961"}]},{"animations":[],"initialState":{"affineTransform":[1,0,0,1,0,0],"masksToBounds":false,"rotation":0,"scale":1,"position":{"pointX":310.0664062500001,"pointY":463.4370002746581},"width":225.9102630615235,"sublayerTransform":[1,0,0,0,0,1,0,0,0,0,1,0,0,0,0,1],"contentsRect":{"y":0,"x":0,"width":1,"height":1},"opacity":0,"edgeAntialiasingMask":15,"height":81.18650054931641,"hidden":false,"anchorPoint":{"pointX":0.5,"pointY":0.5}},"layers":[{"animations":[],"layers":[],"initialState":{"affineTransform":[1,0,0,1,0,0],"masksToBounds":false,"rotation":0,"scale":1,"position":{"pointX":112.9551315307617,"pointY":40.5932502746582},"width":229,"sublayerTransform":[1,0,0,0,0,1,0,0,0,0,1,0,0,0,0,1],"contentsRect":{"y":0,"x":0,"width":1,"height":1},"opacity":1,"edgeAntialiasingMask":0,"height":85,"hidden":false,"anchorPoint":{"pointX":0.4981065775109173,"pointY":0.4992588267606834}},"texture":"13909EA15F3D0356F5B38F505AA6C331"}]}]}}]}